<?xml version="1.0" encoding="UTF-8" standalone="yes"?>
<EEMResp>
    <OpenCaseInfoList>
        <openCaseInfo caseCode="2019070069" caseEndTime="" caseName="0722大雨" caseStartTime="2019/07/22 06:57" cityCode="" disName="水災" eocName="中央災害應變中心" openTier="3"/>
        <openCaseInfo caseCode="2019070069" caseEndTime="" caseName="0722水災三級開設" caseStartTime="2019/07/22 15:35" cityCode="63" disName="水災" eocName="臺北市災害應變中心" openTier="3"/>
    </OpenCaseInfoList>
    <resultCode>S</resultCode>
    <resultText>SUCCESS</resultText>
</EEMResp>
